{
    "code": "200",
    "message": "Success",
    "data": {
        "open": 53.5,
        "high": 53.75,
        "low": 53.22,
        "close": 53.22,
        "pclose": 53.17,
        "volume": 2668,
        "reqDate": "2023-11",
        "feedTime": "1699025543",
        "scId": "IPN01",
        "exchangeId": "N",
        "pivotLevels": [
            {
                "key": "Classic",
                "pivotLevel": {
                    "pivotPoint": "53.62",
                    "r1": "54.50",
                    "r2": "55.82",
                    "r3": "56.70",
                    "s1": "52.30",
                    "s2": "51.42",
                    "s3": "50.10"
                }
            },
            {
                "key": "Fibonacci",
                "pivotLevel": {
                    "pivotPoint": "53.62",
                    "r1": "54.46",
                    "r2": "54.98",
                    "r3": "55.82",
                    "s1": "52.78",
                    "s2": "52.26",
                    "s3": "51.42"
                }
            },
            {
                "key": "Camarilla",
                "pivotLevel": {
                    "pivotPoint": "53.62",
                    "r1": "53.37",
                    "r2": "53.57",
                    "r3": "53.78",
                    "s1": "52.97",
                    "s2": "52.77",
                    "s3": "52.56"
                }
            }
        ],
        "sma": [
            {
                "key": "5",
                "value": "53.22",
                "indication": "Neutral"
            },
            {
                "key": "10",
                "value": "52.73",
                "indication": "Bullish"
            },
            {
                "key": "20",
                "value": null,
                "indication": null
            },
            {
                "key": "50",
                "value": null,
                "indication": null
            },
            {
                "key": "100",
                "value": null,
                "indication": null
            },
            {
                "key": "200",
                "value": null,
                "indication": null
            }
        ],
        "ema": [
            {
                "key": "5",
                "value": "53.09",
                "indication": "Bullish"
            },
            {
                "key": "10",
                "value": "52.57",
                "indication": "Bullish"
            },
            {
                "key": "20",
                "value": null,
                "indication": null
            },
            {
                "key": "50",
                "value": null,
                "indication": null
            },
            {
                "key": "100",
                "value": null,
                "indication": null
            },
            {
                "key": "200",
                "value": null,
                "indication": null
            }
        ],
        "crossover": [
            {
                "key": "5_20",
                "displayValue": "5 & 20 DMA Crossover",
                "indication": null,
                "period": "Short Term"
            },
            {
                "key": "20_50",
                "displayValue": "20 & 50 DMA Crossover",
                "indication": null,
                "period": "Medium Term"
            },
            {
                "key": "50_200",
                "displayValue": "50 & 200 DMA Crossover",
                "indication": null,
                "period": "Long Term"
            }
        ],
        "indicators": [
            {
                "id": "rsi",
                "displayName": "RSI(14)",
                "value": "81.22",
                "indication": "Overbought"
            },
            {
                "id": "macd",
                "displayName": "MACD(12,26,9)",
                "value": null,
                "indication": null
            },
            {
                "id": "stochastic",
                "displayName": "Stochastic(20,3)",
                "value": null,
                "indication": null
            },
            {
                "id": "roc",
                "displayName": "ROC(20)",
                "value": null,
                "indication": null
            },
            {
                "id": "cci",
                "displayName": "CCI(20)",
                "value": null,
                "indication": null
            },
            {
                "id": "williamsR",
                "displayName": "Williamson%R(14)",
                "value": "-72.07",
                "indication": "Bearish"
            },
            {
                "id": "mfi",
                "displayName": "MFI(14)",
                "value": "49.19",
                "indication": "- -"
            },
            {
                "id": "atr",
                "displayName": "ATR(14)",
                "value": "2.39",
                "indication": "- -"
            },
            {
                "id": "adx",
                "displayName": "ADX(14)",
                "value": null,
                "indication": null
            },
            {
                "id": "bollinger",
                "displayName": "Bollinger Band(20,2)",
                "value": [
                    {
                        "id": "upperband",
                        "displayName": "UB",
                        "value": "0.00"
                    },
                    {
                        "id": "lowerband",
                        "displayName": "LB",
                        "value": "0.00"
                    },
                    {
                        "id": "sma20",
                        "displayName": "SMA20",
                        "value": "0.00"
                    }
                ],
                "indication": "- -"
            }
        ],
        "sentiments": {
            "movingAverageSentiment": {
                "bearishCount": 0,
                "bullishCount": 1,
                "neutralCount": 1,
                "indication": "Bullish"
            },
            "movingAverageCrossOverSentiment": {
                "bearishCount": 0,
                "bullishCount": 0,
                "neutralCount": 0,
                "indication": "- -"
            },
            "indicatorsSentiment": {
                "bearishCount": 1,
                "bullishCount": 0,
                "neutralCount": 0,
                "indication": "Bearish"
            },
            "totalBearish": 1,
            "totalBullish": 1,
            "totalNeutral": 1,
            "indication": "Neutral"
        }
    }
}