{
    "code": "200",
    "message": "Success",
    "data": {
        "open": 109.7,
        "high": 113.95,
        "low": 104.45,
        "close": 110.7,
        "pclose": 109.05,
        "volume": 111201,
        "reqDate": "2023-11",
        "feedTime": "1699026283",
        "scId": "IA",
        "exchangeId": "N",
        "pivotLevels": [
            {
                "key": "Classic",
                "pivotLevel": {
                    "pivotPoint": "110.83",
                    "r1": "120.47",
                    "r2": "131.88",
                    "r3": "141.52",
                    "s1": "99.42",
                    "s2": "89.78",
                    "s3": "78.37"
                }
            },
            {
                "key": "Fibonacci",
                "pivotLevel": {
                    "pivotPoint": "110.83",
                    "r1": "118.87",
                    "r2": "123.84",
                    "r3": "131.88",
                    "s1": "102.79",
                    "s2": "97.82",
                    "s3": "89.78"
                }
            },
            {
                "key": "Camarilla",
                "pivotLevel": {
                    "pivotPoint": "110.83",
                    "r1": "110.98",
                    "r2": "112.91",
                    "r3": "114.84",
                    "s1": "107.12",
                    "s2": "105.19",
                    "s3": "103.26"
                }
            }
        ],
        "sma": [
            {
                "key": "5",
                "value": "115.98",
                "indication": "Bearish"
            },
            {
                "key": "10",
                "value": "106.03",
                "indication": "Bullish"
            },
            {
                "key": "20",
                "value": "107.27",
                "indication": "Bullish"
            },
            {
                "key": "50",
                "value": null,
                "indication": null
            },
            {
                "key": "100",
                "value": null,
                "indication": null
            },
            {
                "key": "200",
                "value": null,
                "indication": null
            }
        ],
        "ema": [
            {
                "key": "5",
                "value": "112.53",
                "indication": "Bearish"
            },
            {
                "key": "10",
                "value": "110.67",
                "indication": "Bullish"
            },
            {
                "key": "20",
                "value": "107.27",
                "indication": "Bullish"
            },
            {
                "key": "50",
                "value": null,
                "indication": null
            },
            {
                "key": "100",
                "value": null,
                "indication": null
            },
            {
                "key": "200",
                "value": null,
                "indication": null
            }
        ],
        "crossover": [
            {
                "key": "5_20",
                "displayValue": "5 & 20 DMA Crossover",
                "indication": "Bullish",
                "period": "Short Term"
            },
            {
                "key": "20_50",
                "displayValue": "20 & 50 DMA Crossover",
                "indication": null,
                "period": "Medium Term"
            },
            {
                "key": "50_200",
                "displayValue": "50 & 200 DMA Crossover",
                "indication": null,
                "period": "Long Term"
            }
        ],
        "indicators": [
            {
                "id": "rsi",
                "displayName": "RSI(14)",
                "value": "49.02",
                "indication": "Neutral"
            },
            {
                "id": "macd",
                "displayName": "MACD(12,26,9)",
                "value": null,
                "indication": null
            },
            {
                "id": "stochastic",
                "displayName": "Stochastic(20,3)",
                "value": "38.83",
                "indication": "Bearish"
            },
            {
                "id": "roc",
                "displayName": "ROC(20)",
                "value": null,
                "indication": null
            },
            {
                "id": "cci",
                "displayName": "CCI(20)",
                "value": "4.85",
                "indication": "Neutral"
            },
            {
                "id": "williamsR",
                "displayName": "Williamson%R(14)",
                "value": "-46.26",
                "indication": "Bullish"
            },
            {
                "id": "mfi",
                "displayName": "MFI(14)",
                "value": "62.16",
                "indication": "Neutral"
            },
            {
                "id": "atr",
                "displayName": "ATR(14)",
                "value": "27.14",
                "indication": "- -"
            },
            {
                "id": "adx",
                "displayName": "ADX(14)",
                "value": null,
                "indication": null
            },
            {
                "id": "bollinger",
                "displayName": "Bollinger Band(20,2)",
                "value": [
                    {
                        "id": "upperband",
                        "displayName": "UB",
                        "value": "143.13"
                    },
                    {
                        "id": "lowerband",
                        "displayName": "LB",
                        "value": "71.41"
                    },
                    {
                        "id": "sma20",
                        "displayName": "SMA20",
                        "value": "107.27"
                    }
                ],
                "indication": "- -"
            }
        ],
        "sentiments": {
            "movingAverageSentiment": {
                "bearishCount": 1,
                "bullishCount": 2,
                "neutralCount": 0,
                "indication": "Bullish"
            },
            "movingAverageCrossOverSentiment": {
                "bearishCount": 0,
                "bullishCount": 1,
                "neutralCount": 0,
                "indication": "- -"
            },
            "indicatorsSentiment": {
                "bearishCount": 1,
                "bullishCount": 1,
                "neutralCount": 3,
                "indication": "Neutral"
            },
            "totalBearish": 2,
            "totalBullish": 4,
            "totalNeutral": 3,
            "indication": "Neutral"
        }
    }
}