{
    "code": "200",
    "message": "Success",
    "data": {
        "open": 1897.1,
        "high": 1915.9,
        "low": 1843.55,
        "close": 1860.2,
        "pclose": 1887.15,
        "volume": 35282,
        "reqDate": "2023-11",
        "feedTime": "1699026979",
        "scId": "KIO01",
        "exchangeId": "N",
        "pivotLevels": [
            {
                "key": "Classic",
                "pivotLevel": {
                    "pivotPoint": "1885.92",
                    "r1": "1999.78",
                    "r2": "2112.42",
                    "r3": "2226.28",
                    "s1": "1773.28",
                    "s2": "1659.42",
                    "s3": "1546.78"
                }
            },
            {
                "key": "Fibonacci",
                "pivotLevel": {
                    "pivotPoint": "1885.92",
                    "r1": "1972.44",
                    "r2": "2025.89",
                    "r3": "2112.42",
                    "s1": "1799.39",
                    "s2": "1745.94",
                    "s3": "1659.42"
                }
            },
            {
                "key": "Camarilla",
                "pivotLevel": {
                    "pivotPoint": "1885.92",
                    "r1": "1907.91",
                    "r2": "1928.67",
                    "r3": "1949.44",
                    "s1": "1866.39",
                    "s2": "1845.63",
                    "s3": "1824.86"
                }
            }
        ],
        "sma": [
            {
                "key": "5",
                "value": "1927.25",
                "indication": "Bearish"
            },
            {
                "key": "10",
                "value": "1730.22",
                "indication": "Bullish"
            },
            {
                "key": "20",
                "value": "1556.76",
                "indication": "Bullish"
            },
            {
                "key": "50",
                "value": null,
                "indication": null
            },
            {
                "key": "100",
                "value": null,
                "indication": null
            },
            {
                "key": "200",
                "value": null,
                "indication": null
            }
        ],
        "ema": [
            {
                "key": "5",
                "value": "1866.59",
                "indication": "Bearish"
            },
            {
                "key": "10",
                "value": "1770.91",
                "indication": "Bullish"
            },
            {
                "key": "20",
                "value": "1611.13",
                "indication": "Bullish"
            },
            {
                "key": "50",
                "value": null,
                "indication": null
            },
            {
                "key": "100",
                "value": null,
                "indication": null
            },
            {
                "key": "200",
                "value": null,
                "indication": null
            }
        ],
        "crossover": [
            {
                "key": "5_20",
                "displayValue": "5 & 20 DMA Crossover",
                "indication": "Bullish",
                "period": "Short Term"
            },
            {
                "key": "20_50",
                "displayValue": "20 & 50 DMA Crossover",
                "indication": null,
                "period": "Medium Term"
            },
            {
                "key": "50_200",
                "displayValue": "50 & 200 DMA Crossover",
                "indication": null,
                "period": "Long Term"
            }
        ],
        "indicators": [
            {
                "id": "rsi",
                "displayName": "RSI(14)",
                "value": "66.53",
                "indication": "Bullish"
            },
            {
                "id": "macd",
                "displayName": "MACD(12,26,9)",
                "value": "198.42",
                "indication": "Bullish"
            },
            {
                "id": "stochastic",
                "displayName": "Stochastic(20,3)",
                "value": "66.89",
                "indication": "Bullish"
            },
            {
                "id": "roc",
                "displayName": "ROC(20)",
                "value": "34.49",
                "indication": "Bullish"
            },
            {
                "id": "cci",
                "displayName": "CCI(20)",
                "value": "102.43",
                "indication": "Bullish"
            },
            {
                "id": "williamsR",
                "displayName": "Williamson%R(14)",
                "value": "-39.00",
                "indication": "Bullish"
            },
            {
                "id": "mfi",
                "displayName": "MFI(14)",
                "value": "74.43",
                "indication": "Neutral"
            },
            {
                "id": "atr",
                "displayName": "ATR(14)",
                "value": "218.71",
                "indication": "High Volatility"
            },
            {
                "id": "adx",
                "displayName": "ADX(14)",
                "value": "43.70",
                "indication": "Strong Trend"
            },
            {
                "id": "bollinger",
                "displayName": "Bollinger Band(20,2)",
                "value": [
                    {
                        "id": "upperband",
                        "displayName": "UB",
                        "value": "2068.90"
                    },
                    {
                        "id": "lowerband",
                        "displayName": "LB",
                        "value": "1044.62"
                    },
                    {
                        "id": "sma20",
                        "displayName": "SMA20",
                        "value": "1556.76"
                    }
                ],
                "indication": "- -"
            }
        ],
        "sentiments": {
            "movingAverageSentiment": {
                "bearishCount": 1,
                "bullishCount": 2,
                "neutralCount": 0,
                "indication": "Bullish"
            },
            "movingAverageCrossOverSentiment": {
                "bearishCount": 0,
                "bullishCount": 1,
                "neutralCount": 0,
                "indication": "- -"
            },
            "indicatorsSentiment": {
                "bearishCount": 0,
                "bullishCount": 6,
                "neutralCount": 1,
                "indication": "Bullish"
            },
            "totalBearish": 1,
            "totalBullish": 9,
            "totalNeutral": 1,
            "indication": "Bullish"
        }
    }
}